gemseo_umdo/__init__.py
gemseo_umdo/monte_carlo_sampler.py
gemseo_umdo/_utils/__init__.py
gemseo_umdo/_utils/compatibility/__init__.py
gemseo_umdo/_utils/compatibility/numpy.py
gemseo_umdo/_utils/compatibility/openturns.py
gemseo_umdo/disciplines/__init__.py
gemseo_umdo/disciplines/additive_noiser.py
gemseo_umdo/disciplines/base_noiser.py
gemseo_umdo/disciplines/multiplicative_noiser.py
gemseo_umdo/disciplines/noiser_factory.py
gemseo_umdo/disciplines/utils.py
gemseo_umdo/formulations/__init__.py
gemseo_umdo/formulations/base_sampling_settings.py
gemseo_umdo/formulations/base_surrogate_settings.py
gemseo_umdo/formulations/base_umdo_formulation.py
gemseo_umdo/formulations/base_umdo_formulation_settings.py
gemseo_umdo/formulations/control_variate.py
gemseo_umdo/formulations/control_variate_settings.py
gemseo_umdo/formulations/factory.py
gemseo_umdo/formulations/pce.py
gemseo_umdo/formulations/pce_settings.py
gemseo_umdo/formulations/sampling.py
gemseo_umdo/formulations/sampling_settings.py
gemseo_umdo/formulations/sequential_sampling.py
gemseo_umdo/formulations/sequential_sampling_settings.py
gemseo_umdo/formulations/surrogate.py
gemseo_umdo/formulations/surrogate_settings.py
gemseo_umdo/formulations/taylor_polynomial.py
gemseo_umdo/formulations/taylor_polynomial_settings.py
gemseo_umdo/formulations/_functions/__init__.py
gemseo_umdo/formulations/_functions/base_statistic_function.py
gemseo_umdo/formulations/_functions/base_statistic_function_for_sampling.py
gemseo_umdo/formulations/_functions/hessian_function.py
gemseo_umdo/formulations/_functions/iterative_estimation.py
gemseo_umdo/formulations/_functions/statistic_function_for_control_variate.py
gemseo_umdo/formulations/_functions/statistic_function_for_iterative_sampling.py
gemseo_umdo/formulations/_functions/statistic_function_for_pce.py
gemseo_umdo/formulations/_functions/statistic_function_for_standard_sampling.py
gemseo_umdo/formulations/_functions/statistic_function_for_surrogate.py
gemseo_umdo-4.3.0.dist-info/licenses/LICENSE.txt
gemseo_umdo-4.3.0.dist-info/METADATA
gemseo_umdo-4.3.0.dist-info/WHEEL
gemseo_umdo-4.3.0.dist-info/entry_points.txt
gemseo_umdo-4.3.0.dist-info/top_level.txt
gemseo_umdo-4.3.0.dist-info/RECORD
